<?xml version="1.0" encoding="utf-8"?>
<LanguageData>
<Apparel_KidHelmet.label>Mũ bảo hiểm trẻ em</Apparel_KidHelmet.label>
<Apparel_KidHelmet.description>Mũ bảo hiểm nhỏ gọn thiết kế cho trẻ em, có khả năng bảo vệ khỏi một số loại vũ khí sắc bén. Chỉ bảo vệ phần đầu, không hiệu quả với vũ khí đập. Tuy nhiên, việc sử dụng mũ bảo hiểm này trong chiến đấu có nghĩa là tình hình đã rất nghiêm trọng.</Apparel_KidHelmet.description>
<Apparel_KidPants.label>Quần trẻ em</Apparel_KidPants.label>
<Apparel_KidPants.description>Quần thiết kế nhỏ gọn cho trẻ em.</Apparel_KidPants.description>
<Apparel_KidParka.label>Áo khoác trẻ em</Apparel_KidParka.label>
<Apparel_KidParka.description>Áo khoác dày thiết kế cho trẻ em, giữ ấm ngay cả trong điều kiện lạnh nhất.</Apparel_KidParka.description>
<Apparel_KidRomper.label>Áo liền quần trẻ em</Apparel_KidRomper.label>
<Apparel_KidRomper.description>Áo liền quần nhỏ gọn thiết kế cho trẻ em, kết hợp giữa áo phông, quần và đồ lót. Trẻ em rất thích loại trang phục này!</Apparel_KidRomper.description>
<Apparel_KidShirt.label>Áo sơ mi trẻ em</Apparel_KidShirt.label>
<Apparel_KidShirt.description>Áo sơ mi nhỏ gọn thiết kế cho trẻ em.</Apparel_KidShirt.description>
<Apparel_KidTribal.label>Trang phục bộ lạc trẻ em</Apparel_KidTribal.label>
<Apparel_KidTribal.description>Trang phục bộ lạc nhỏ gọn thiết kế cho trẻ em, được làm từ công cụ nguyên thủy. Mặc dù trông có vẻ lạc hậu, nhưng khả năng giữ nhiệt của nó khá tốt.</Apparel_KidTribal.description>
</LanguageData>