<?xml version="1.0" encoding="utf-8"?>
<LanguageData>
<Mote_RitualGlowRays.label>Hạt vi mô</Mote_RitualGlowRays.label>
<Mote_RitualGlowSingleRay.label>Hạt vi mô</Mote_RitualGlowSingleRay.label>
<Mote_RitualSmoke.label>Hạt vi mô</Mote_RitualSmoke.label>
<Mote_RitualSmokeDust.label>Hạt vi mô</Mote_RitualSmokeDust.label>
<Mote_RitualSmokeDustVague.label>Hạt vi mô</Mote_RitualSmokeDustVague.label>
<Mote_RitualSmokeThick.label>Hạt vi mô</Mote_RitualSmokeThick.label>
<Mote_RitualSmokeThickSlim.label>Hạt vi mô</Mote_RitualSmokeThickSlim.label>
<Mote_RitualTechLineA.label>Hạt vi mô</Mote_RitualTechLineA.label>
<Mote_RitualTechLineB.label>Hạt vi mô</Mote_RitualTechLineB.label>
<Mote_RitualTechLineC.label>Hạt vi mô</Mote_RitualTechLineC.label>
<Mote_RolePawnHighlight.label>Hạt vi mô</Mote_RolePawnHighlight.label>
<Mote_RolePositionHighlight.label>Hạt vi mô</Mote_RolePositionHighlight.label>
<Mote_SpikePipe.label>Hạt vi mô</Mote_SpikePipe.label>
<Mote_TotemOutline.label>Hạt vi mô</Mote_TotemOutline.label>
</LanguageData>